{
  "session": "14710",
  "companyCount": 3,
  "headlineCount": 9,
  "companies": [
    {
      "companyId": 0,
      "name": "Jovik Asset Group",
      "headlineCount": 4,
      "firstBarIx": 1,
      "headlineIds": [
        "H001",
        "H003",
        "H005",
        "H007"
      ],
      "sampleHeadlines": [
        "Jovik Asset Group schedules annual shareholder meeting for next month",
        "Jovik Asset Group announces $6.3B share buyback program",
        "Jovik Asset Group secures $320M contract with a leading cloud platform"
      ]
    },
    {
      "companyId": 1,
      "name": "Talvix Holdings",
      "headlineCount": 1,
      "firstBarIx": 5,
      "headlineIds": [
        "H002"
      ],
      "sampleHeadlines": [
        "Talvix Holdings explores strategic alternatives for process automation unit"
      ]
    },
    {
      "companyId": 2,
      "name": "Zrovov Advisors",
      "headlineCount": 4,
      "firstBarIx": 10,
      "headlineIds": [
        "H004",
        "H006",
        "H008",
        "H009"
      ],
      "sampleHeadlines": [
        "Zrovov Advisors secures $500M contract with a top-tier research institute",
        "Zrovov Advisors sees 8% drop in new customer orders this quarter",
        "Zrovov Advisors reports strong demand in North America, raises outlook"
      ]
    }
  ],
  "headlines": [
    {
      "headlineId": "H001",
      "barIx": 1,
      "companyId": 0,
      "companyName": "Jovik Asset Group",
      "headline": "Jovik Asset Group schedules annual shareholder meeting for next month"
    },
    {
      "headlineId": "H002",
      "barIx": 5,
      "companyId": 1,
      "companyName": "Talvix Holdings",
      "headline": "Talvix Holdings explores strategic alternatives for process automation unit"
    },
    {
      "headlineId": "H003",
      "barIx": 5,
      "companyId": 0,
      "companyName": "Jovik Asset Group",
      "headline": "Jovik Asset Group announces $6.3B share buyback program"
    },
    {
      "headlineId": "H004",
      "barIx": 10,
      "companyId": 2,
      "companyName": "Zrovov Advisors",
      "headline": "Zrovov Advisors secures $500M contract with a top-tier research institute"
    },
    {
      "headlineId": "H005",
      "barIx": 23,
      "companyId": 0,
      "companyName": "Jovik Asset Group",
      "headline": "Jovik Asset Group secures $320M contract with a leading cloud platform"
    },
    {
      "headlineId": "H006",
      "barIx": 31,
      "companyId": 2,
      "companyName": "Zrovov Advisors",
      "headline": "Zrovov Advisors sees 8% drop in new customer orders this quarter"
    },
    {
      "headlineId": "H007",
      "barIx": 33,
      "companyId": 0,
      "companyName": "Jovik Asset Group",
      "headline": "Jovik Asset Group secures $50M contract with an international consortium"
    },
    {
      "headlineId": "H008",
      "barIx": 40,
      "companyId": 2,
      "companyName": "Zrovov Advisors",
      "headline": "Zrovov Advisors reports strong demand in North America, raises outlook"
    },
    {
      "headlineId": "H009",
      "barIx": 48,
      "companyId": 2,
      "companyName": "Zrovov Advisors",
      "headline": "Zrovov Advisors launches next-generation wireless connectivity platform"
    }
  ]
}