{
  "session": "4844",
  "companyCount": 4,
  "headlineCount": 9,
  "companies": [
    {
      "companyId": 0,
      "name": "Wyrnik Sciences",
      "headlineCount": 2,
      "firstBarIx": 8,
      "headlineIds": [
        "H001",
        "H003"
      ],
      "sampleHeadlines": [
        "Wyrnik Sciences sees mixed results in renewable storage pilot program",
        "Wyrnik Sciences secures $50M contract with an international consortium"
      ]
    },
    {
      "companyId": 1,
      "name": "Myrnon Therapeutics",
      "headlineCount": 4,
      "firstBarIx": 9,
      "headlineIds": [
        "H002",
        "H004",
        "H005",
        "H006"
      ],
      "sampleHeadlines": [
        "Myrnon Therapeutics reports record quarterly revenue, up 18% year-over-year",
        "Myrnon Therapeutics files for regulatory approval of new automated logistics offering",
        "Myrnon Therapeutics completes strategic acquisition to strengthen enterprise software"
      ]
    },
    {
      "companyId": 2,
      "name": "Nolvav Commerce",
      "headlineCount": 2,
      "firstBarIx": 38,
      "headlineIds": [
        "H007",
        "H009"
      ],
      "sampleHeadlines": [
        "Nolvav Commerce Chief Operating Officer steps down unexpectedly citing personal reasons",
        "Nolvav Commerce secures $500M contract with a top-tier research institute"
      ]
    },
    {
      "companyId": 3,
      "name": "Frelis Genomics",
      "headlineCount": 1,
      "firstBarIx": 46,
      "headlineIds": [
        "H008"
      ],
      "sampleHeadlines": [
        "Frelis Genomics board meeting to discuss major strategic initiative"
      ]
    }
  ],
  "headlines": [
    {
      "headlineId": "H001",
      "barIx": 8,
      "companyId": 0,
      "companyName": "Wyrnik Sciences",
      "headline": "Wyrnik Sciences sees mixed results in renewable storage pilot program"
    },
    {
      "headlineId": "H002",
      "barIx": 9,
      "companyId": 1,
      "companyName": "Myrnon Therapeutics",
      "headline": "Myrnon Therapeutics reports record quarterly revenue, up 18% year-over-year"
    },
    {
      "headlineId": "H003",
      "barIx": 27,
      "companyId": 0,
      "companyName": "Wyrnik Sciences",
      "headline": "Wyrnik Sciences secures $50M contract with an international consortium"
    },
    {
      "headlineId": "H004",
      "barIx": 29,
      "companyId": 1,
      "companyName": "Myrnon Therapeutics",
      "headline": "Myrnon Therapeutics files for regulatory approval of new automated logistics offering"
    },
    {
      "headlineId": "H005",
      "barIx": 31,
      "companyId": 1,
      "companyName": "Myrnon Therapeutics",
      "headline": "Myrnon Therapeutics completes strategic acquisition to strengthen enterprise software"
    },
    {
      "headlineId": "H006",
      "barIx": 32,
      "companyId": 1,
      "companyName": "Myrnon Therapeutics",
      "headline": "Myrnon Therapeutics secures $75M contract with an international consortium"
    },
    {
      "headlineId": "H007",
      "barIx": 38,
      "companyId": 2,
      "companyName": "Nolvav Commerce",
      "headline": "Nolvav Commerce Chief Operating Officer steps down unexpectedly citing personal reasons"
    },
    {
      "headlineId": "H008",
      "barIx": 46,
      "companyId": 3,
      "companyName": "Frelis Genomics",
      "headline": "Frelis Genomics board meeting to discuss major strategic initiative"
    },
    {
      "headlineId": "H009",
      "barIx": 49,
      "companyId": 2,
      "companyName": "Nolvav Commerce",
      "headline": "Nolvav Commerce secures $500M contract with a top-tier research institute"
    }
  ]
}