{
  "session": "18910",
  "companyCount": 2,
  "headlineCount": 8,
  "companies": [
    {
      "companyId": 0,
      "name": "Jorvyl Securities",
      "headlineCount": 6,
      "firstBarIx": 0,
      "headlineIds": [
        "H001",
        "H002",
        "H003",
        "H004",
        "H006",
        "H008"
      ],
      "sampleHeadlines": [
        "Jorvyl Securities completes strategic acquisition to strengthen data analytics",
        "Jorvyl Securities completes strategic acquisition to strengthen wireless connectivity",
        "Jorvyl Securities misses quarterly revenue estimates by 3%"
      ]
    },
    {
      "companyId": 1,
      "name": "Arnik Commerce",
      "headlineCount": 2,
      "firstBarIx": 13,
      "headlineIds": [
        "H005",
        "H007"
      ],
      "sampleHeadlines": [
        "Arnik Commerce announces $4.1B share buyback program",
        "Arnik Commerce explores strategic alternatives for digital payments unit"
      ]
    }
  ],
  "headlines": [
    {
      "headlineId": "H001",
      "barIx": 0,
      "companyId": 0,
      "companyName": "Jorvyl Securities",
      "headline": "Jorvyl Securities completes strategic acquisition to strengthen data analytics"
    },
    {
      "headlineId": "H002",
      "barIx": 2,
      "companyId": 0,
      "companyName": "Jorvyl Securities",
      "headline": "Jorvyl Securities completes strategic acquisition to strengthen wireless connectivity"
    },
    {
      "headlineId": "H003",
      "barIx": 9,
      "companyId": 0,
      "companyName": "Jorvyl Securities",
      "headline": "Jorvyl Securities misses quarterly revenue estimates by 3%"
    },
    {
      "headlineId": "H004",
      "barIx": 12,
      "companyId": 0,
      "companyName": "Jorvyl Securities",
      "headline": "Jorvyl Securities secures $120M contract with a major logistics provider"
    },
    {
      "headlineId": "H005",
      "barIx": 13,
      "companyId": 1,
      "companyName": "Arnik Commerce",
      "headline": "Arnik Commerce announces $4.1B share buyback program"
    },
    {
      "headlineId": "H006",
      "barIx": 14,
      "companyId": 0,
      "companyName": "Jorvyl Securities",
      "headline": "Jorvyl Securities confirms participation in Emerging Markets Forum"
    },
    {
      "headlineId": "H007",
      "barIx": 30,
      "companyId": 1,
      "companyName": "Arnik Commerce",
      "headline": "Arnik Commerce explores strategic alternatives for digital payments unit"
    },
    {
      "headlineId": "H008",
      "barIx": 31,
      "companyId": 0,
      "companyName": "Jorvyl Securities",
      "headline": "Jorvyl Securities sees 8% drop in new customer orders this quarter"
    }
  ]
}