{
  "session": "12883",
  "companyCount": 4,
  "headlineCount": 16,
  "companies": [
    {
      "companyId": 0,
      "name": "Varvov Retail Group",
      "headlineCount": 6,
      "firstBarIx": 0,
      "headlineIds": [
        "H001",
        "H003",
        "H004",
        "H008",
        "H012",
        "H013"
      ],
      "sampleHeadlines": [
        "Varvov Retail Group explores strategic alternatives for precision manufacturing unit",
        "Varvov Retail Group wins industry award for excellence in cloud infrastructure",
        "Varvov Retail Group sees mixed results in cloud infrastructure pilot program"
      ]
    },
    {
      "companyId": 1,
      "name": "Arnos Marketplace",
      "headlineCount": 3,
      "firstBarIx": 9,
      "headlineIds": [
        "H002",
        "H010",
        "H014"
      ],
      "sampleHeadlines": [
        "Arnos Marketplace faces regulatory review of enterprise software practices",
        "Arnos Marketplace sees 25% drop in new customer orders this quarter",
        "Arnos Marketplace completes planned facility upgrade in North America"
      ]
    },
    {
      "companyId": 2,
      "name": "Orevar Marketplace",
      "headlineCount": 2,
      "firstBarIx": 20,
      "headlineIds": [
        "H005",
        "H015"
      ],
      "sampleHeadlines": [
        "Orevar Marketplace secures $50M contract with a top-tier research institute",
        "Orevar Marketplace files routine patent applications in automated logistics"
      ]
    },
    {
      "companyId": 3,
      "name": "Yorven Labs",
      "headlineCount": 5,
      "firstBarIx": 23,
      "headlineIds": [
        "H006",
        "H007",
        "H009",
        "H011",
        "H016"
      ],
      "sampleHeadlines": [
        "Yorven Labs withdraws from Latin America market citing unfavorable conditions",
        "Yorven Labs warns of supply chain disruptions affecting Asia Pacific operations",
        "Yorven Labs reports strong demand in Europe, raises outlook"
      ]
    }
  ],
  "headlines": [
    {
      "headlineId": "H001",
      "barIx": 0,
      "companyId": 0,
      "companyName": "Varvov Retail Group",
      "headline": "Varvov Retail Group explores strategic alternatives for precision manufacturing unit"
    },
    {
      "headlineId": "H002",
      "barIx": 9,
      "companyId": 1,
      "companyName": "Arnos Marketplace",
      "headline": "Arnos Marketplace faces regulatory review of enterprise software practices"
    },
    {
      "headlineId": "H003",
      "barIx": 9,
      "companyId": 0,
      "companyName": "Varvov Retail Group",
      "headline": "Varvov Retail Group wins industry award for excellence in cloud infrastructure"
    },
    {
      "headlineId": "H004",
      "barIx": 14,
      "companyId": 0,
      "companyName": "Varvov Retail Group",
      "headline": "Varvov Retail Group sees mixed results in cloud infrastructure pilot program"
    },
    {
      "headlineId": "H005",
      "barIx": 20,
      "companyId": 2,
      "companyName": "Orevar Marketplace",
      "headline": "Orevar Marketplace secures $50M contract with a top-tier research institute"
    },
    {
      "headlineId": "H006",
      "barIx": 23,
      "companyId": 3,
      "companyName": "Yorven Labs",
      "headline": "Yorven Labs withdraws from Latin America market citing unfavorable conditions"
    },
    {
      "headlineId": "H007",
      "barIx": 23,
      "companyId": 3,
      "companyName": "Yorven Labs",
      "headline": "Yorven Labs warns of supply chain disruptions affecting Asia Pacific operations"
    },
    {
      "headlineId": "H008",
      "barIx": 28,
      "companyId": 0,
      "companyName": "Varvov Retail Group",
      "headline": "Varvov Retail Group completes strategic acquisition to strengthen automated logistics"
    },
    {
      "headlineId": "H009",
      "barIx": 28,
      "companyId": 3,
      "companyName": "Yorven Labs",
      "headline": "Yorven Labs reports strong demand in Europe, raises outlook"
    },
    {
      "headlineId": "H010",
      "barIx": 29,
      "companyId": 1,
      "companyName": "Arnos Marketplace",
      "headline": "Arnos Marketplace sees 25% drop in new customer orders this quarter"
    },
    {
      "headlineId": "H011",
      "barIx": 32,
      "companyId": 3,
      "companyName": "Yorven Labs",
      "headline": "Yorven Labs secures $650M contract with a multinational manufacturer"
    },
    {
      "headlineId": "H012",
      "barIx": 33,
      "companyId": 0,
      "companyName": "Varvov Retail Group",
      "headline": "Varvov Retail Group enters joint venture with an international consortium"
    },
    {
      "headlineId": "H013",
      "barIx": 37,
      "companyId": 0,
      "companyName": "Varvov Retail Group",
      "headline": "Varvov Retail Group files for regulatory approval of new supply chain optimization offering"
    },
    {
      "headlineId": "H014",
      "barIx": 38,
      "companyId": 1,
      "companyName": "Arnos Marketplace",
      "headline": "Arnos Marketplace completes planned facility upgrade in North America"
    },
    {
      "headlineId": "H015",
      "barIx": 38,
      "companyId": 2,
      "companyName": "Orevar Marketplace",
      "headline": "Orevar Marketplace files routine patent applications in automated logistics"
    },
    {
      "headlineId": "H016",
      "barIx": 49,
      "companyId": 3,
      "companyName": "Yorven Labs",
      "headline": "Yorven Labs secures $320M contract with a global retailer"
    }
  ]
}