{
  "session": "4165",
  "companyCount": 4,
  "headlineCount": 7,
  "companies": [
    {
      "companyId": 0,
      "name": "Ulvyn Microchips",
      "headlineCount": 2,
      "firstBarIx": 10,
      "headlineIds": [
        "H001",
        "H005"
      ],
      "sampleHeadlines": [
        "Ulvyn Microchips misses quarterly revenue estimates by 3%",
        "Ulvyn Microchips launches next-generation data analytics platform"
      ]
    },
    {
      "companyId": 1,
      "name": "Nolvis Devices",
      "headlineCount": 3,
      "firstBarIx": 12,
      "headlineIds": [
        "H002",
        "H003",
        "H007"
      ],
      "sampleHeadlines": [
        "Nolvis Devices delays product launch in precision manufacturing segment",
        "Nolvis Devices secures $50M contract with a multinational manufacturer",
        "Nolvis Devices begins scheduled maintenance of digital payments systems"
      ]
    },
    {
      "companyId": 2,
      "name": "Yorven Labs",
      "headlineCount": 1,
      "firstBarIx": 19,
      "headlineIds": [
        "H004"
      ],
      "sampleHeadlines": [
        "Yorven Labs warns of supply chain disruptions affecting North America operations"
      ]
    },
    {
      "companyId": 3,
      "name": "Talvep Computing",
      "headlineCount": 1,
      "firstBarIx": 31,
      "headlineIds": [
        "H006"
      ],
      "sampleHeadlines": [
        "Talvep Computing reports 7% decline in operating income"
      ]
    }
  ],
  "headlines": [
    {
      "headlineId": "H001",
      "barIx": 10,
      "companyId": 0,
      "companyName": "Ulvyn Microchips",
      "headline": "Ulvyn Microchips misses quarterly revenue estimates by 3%"
    },
    {
      "headlineId": "H002",
      "barIx": 12,
      "companyId": 1,
      "companyName": "Nolvis Devices",
      "headline": "Nolvis Devices delays product launch in precision manufacturing segment"
    },
    {
      "headlineId": "H003",
      "barIx": 18,
      "companyId": 1,
      "companyName": "Nolvis Devices",
      "headline": "Nolvis Devices secures $50M contract with a multinational manufacturer"
    },
    {
      "headlineId": "H004",
      "barIx": 19,
      "companyId": 2,
      "companyName": "Yorven Labs",
      "headline": "Yorven Labs warns of supply chain disruptions affecting North America operations"
    },
    {
      "headlineId": "H005",
      "barIx": 21,
      "companyId": 0,
      "companyName": "Ulvyn Microchips",
      "headline": "Ulvyn Microchips launches next-generation data analytics platform"
    },
    {
      "headlineId": "H006",
      "barIx": 31,
      "companyId": 3,
      "companyName": "Talvep Computing",
      "headline": "Talvep Computing reports 7% decline in operating income"
    },
    {
      "headlineId": "H007",
      "barIx": 34,
      "companyId": 1,
      "companyName": "Nolvis Devices",
      "headline": "Nolvis Devices begins scheduled maintenance of digital payments systems"
    }
  ]
}