{
  "session": "14897",
  "companyCount": 4,
  "headlineCount": 6,
  "companies": [
    {
      "companyId": 0,
      "name": "Kelvik Power",
      "headlineCount": 2,
      "firstBarIx": 8,
      "headlineIds": [
        "H001",
        "H002"
      ],
      "sampleHeadlines": [
        "Kelvik Power revises long-term strategy with focus on precision manufacturing",
        "Kelvik Power signs multi-year partnership with a multinational manufacturer"
      ]
    },
    {
      "companyId": 1,
      "name": "Ulvyn Microchips",
      "headlineCount": 2,
      "firstBarIx": 30,
      "headlineIds": [
        "H003",
        "H004"
      ],
      "sampleHeadlines": [
        "Ulvyn Microchips opens new office in Europe",
        "Ulvyn Microchips files for regulatory approval of new renewable storage offering"
      ]
    },
    {
      "companyId": 2,
      "name": "Zrovex Industries",
      "headlineCount": 1,
      "firstBarIx": 36,
      "headlineIds": [
        "H005"
      ],
      "sampleHeadlines": [
        "Zrovex Industries completes strategic acquisition to strengthen precision manufacturing"
      ]
    },
    {
      "companyId": 3,
      "name": "Plevik Energy",
      "headlineCount": 1,
      "firstBarIx": 38,
      "headlineIds": [
        "H006"
      ],
      "sampleHeadlines": [
        "Plevik Energy secures $50M contract with an international consortium"
      ]
    }
  ],
  "headlines": [
    {
      "headlineId": "H001",
      "barIx": 8,
      "companyId": 0,
      "companyName": "Kelvik Power",
      "headline": "Kelvik Power revises long-term strategy with focus on precision manufacturing"
    },
    {
      "headlineId": "H002",
      "barIx": 11,
      "companyId": 0,
      "companyName": "Kelvik Power",
      "headline": "Kelvik Power signs multi-year partnership with a multinational manufacturer"
    },
    {
      "headlineId": "H003",
      "barIx": 30,
      "companyId": 1,
      "companyName": "Ulvyn Microchips",
      "headline": "Ulvyn Microchips opens new office in Europe"
    },
    {
      "headlineId": "H004",
      "barIx": 30,
      "companyId": 1,
      "companyName": "Ulvyn Microchips",
      "headline": "Ulvyn Microchips files for regulatory approval of new renewable storage offering"
    },
    {
      "headlineId": "H005",
      "barIx": 36,
      "companyId": 2,
      "companyName": "Zrovex Industries",
      "headline": "Zrovex Industries completes strategic acquisition to strengthen precision manufacturing"
    },
    {
      "headlineId": "H006",
      "barIx": 38,
      "companyId": 3,
      "companyName": "Plevik Energy",
      "headline": "Plevik Energy secures $50M contract with an international consortium"
    }
  ]
}