{
  "session": "18645",
  "companyCount": 4,
  "headlineCount": 11,
  "companies": [
    {
      "companyId": 0,
      "name": "Zelval Energy",
      "headlineCount": 4,
      "firstBarIx": 3,
      "headlineIds": [
        "H001",
        "H002",
        "H010",
        "H011"
      ],
      "sampleHeadlines": [
        "Zelval Energy announces breakthrough in automated logistics",
        "Zelval Energy to host investor day focused on supply chain optimization strategy",
        "Zelval Energy sees 7% margin improvement in latest quarter"
      ]
    },
    {
      "companyId": 1,
      "name": "Plevik Energy",
      "headlineCount": 4,
      "firstBarIx": 6,
      "headlineIds": [
        "H003",
        "H004",
        "H005",
        "H007"
      ],
      "sampleHeadlines": [
        "Plevik Energy launches next-generation process automation platform",
        "Plevik Energy files for regulatory approval of new enterprise software offering",
        "Plevik Energy reports 8% increase in customer acquisition"
      ]
    },
    {
      "companyId": 2,
      "name": "Joval Brands",
      "headlineCount": 2,
      "firstBarIx": 15,
      "headlineIds": [
        "H006",
        "H009"
      ],
      "sampleHeadlines": [
        "Joval Brands completes strategic acquisition to strengthen automated logistics",
        "Joval Brands withdraws from Middle East market citing unfavorable conditions"
      ]
    },
    {
      "companyId": 3,
      "name": "Nolvol Resources",
      "headlineCount": 1,
      "firstBarIx": 23,
      "headlineIds": [
        "H008"
      ],
      "sampleHeadlines": [
        "Nolvol Resources secures $250M contract with a top-tier research institute"
      ]
    }
  ],
  "headlines": [
    {
      "headlineId": "H001",
      "barIx": 3,
      "companyId": 0,
      "companyName": "Zelval Energy",
      "headline": "Zelval Energy announces breakthrough in automated logistics"
    },
    {
      "headlineId": "H002",
      "barIx": 5,
      "companyId": 0,
      "companyName": "Zelval Energy",
      "headline": "Zelval Energy to host investor day focused on supply chain optimization strategy"
    },
    {
      "headlineId": "H003",
      "barIx": 6,
      "companyId": 1,
      "companyName": "Plevik Energy",
      "headline": "Plevik Energy launches next-generation process automation platform"
    },
    {
      "headlineId": "H004",
      "barIx": 9,
      "companyId": 1,
      "companyName": "Plevik Energy",
      "headline": "Plevik Energy files for regulatory approval of new enterprise software offering"
    },
    {
      "headlineId": "H005",
      "barIx": 14,
      "companyId": 1,
      "companyName": "Plevik Energy",
      "headline": "Plevik Energy reports 8% increase in customer acquisition"
    },
    {
      "headlineId": "H006",
      "barIx": 15,
      "companyId": 2,
      "companyName": "Joval Brands",
      "headline": "Joval Brands completes strategic acquisition to strengthen automated logistics"
    },
    {
      "headlineId": "H007",
      "barIx": 16,
      "companyId": 1,
      "companyName": "Plevik Energy",
      "headline": "Plevik Energy to host investor day focused on automated logistics strategy"
    },
    {
      "headlineId": "H008",
      "barIx": 23,
      "companyId": 3,
      "companyName": "Nolvol Resources",
      "headline": "Nolvol Resources secures $250M contract with a top-tier research institute"
    },
    {
      "headlineId": "H009",
      "barIx": 24,
      "companyId": 2,
      "companyName": "Joval Brands",
      "headline": "Joval Brands withdraws from Middle East market citing unfavorable conditions"
    },
    {
      "headlineId": "H010",
      "barIx": 48,
      "companyId": 0,
      "companyName": "Zelval Energy",
      "headline": "Zelval Energy sees 7% margin improvement in latest quarter"
    },
    {
      "headlineId": "H011",
      "barIx": 49,
      "companyId": 0,
      "companyName": "Zelval Energy",
      "headline": "Zelval Energy faces class action over renewable storage service disruption"
    }
  ]
}