{
  "session": "19078",
  "companyCount": 4,
  "headlineCount": 12,
  "companies": [
    {
      "companyId": 0,
      "name": "Zrovex Industries",
      "headlineCount": 4,
      "firstBarIx": 4,
      "headlineIds": [
        "H001",
        "H003",
        "H006",
        "H008"
      ],
      "sampleHeadlines": [
        "Zrovex Industries faces regulatory review of process automation practices",
        "Zrovex Industries files routine patent applications in digital payments",
        "Zrovex Industries wins industry award for excellence in renewable storage"
      ]
    },
    {
      "companyId": 1,
      "name": "Xovep Stores",
      "headlineCount": 3,
      "firstBarIx": 5,
      "headlineIds": [
        "H002",
        "H005",
        "H010"
      ],
      "sampleHeadlines": [
        "Xovep Stores revises long-term strategy with focus on supply chain optimization",
        "Xovep Stores begins scheduled maintenance of automated logistics systems",
        "Xovep Stores sees 15% drop in new customer orders this quarter"
      ]
    },
    {
      "companyId": 2,
      "name": "Nerven Grid",
      "headlineCount": 3,
      "firstBarIx": 17,
      "headlineIds": [
        "H004",
        "H009",
        "H012"
      ],
      "sampleHeadlines": [
        "Nerven Grid faces regulatory review of digital payments practices",
        "Nerven Grid expands operations into Europe markets",
        "Nerven Grid reports rising costs pressuring margins in renewable storage"
      ]
    },
    {
      "companyId": 3,
      "name": "Orevex Renewables",
      "headlineCount": 2,
      "firstBarIx": 29,
      "headlineIds": [
        "H007",
        "H011"
      ],
      "sampleHeadlines": [
        "Orevex Renewables faces regulatory review of precision manufacturing practices",
        "Orevex Renewables enters joint venture with a multinational manufacturer"
      ]
    }
  ],
  "headlines": [
    {
      "headlineId": "H001",
      "barIx": 4,
      "companyId": 0,
      "companyName": "Zrovex Industries",
      "headline": "Zrovex Industries faces regulatory review of process automation practices"
    },
    {
      "headlineId": "H002",
      "barIx": 5,
      "companyId": 1,
      "companyName": "Xovep Stores",
      "headline": "Xovep Stores revises long-term strategy with focus on supply chain optimization"
    },
    {
      "headlineId": "H003",
      "barIx": 7,
      "companyId": 0,
      "companyName": "Zrovex Industries",
      "headline": "Zrovex Industries files routine patent applications in digital payments"
    },
    {
      "headlineId": "H004",
      "barIx": 17,
      "companyId": 2,
      "companyName": "Nerven Grid",
      "headline": "Nerven Grid faces regulatory review of digital payments practices"
    },
    {
      "headlineId": "H005",
      "barIx": 24,
      "companyId": 1,
      "companyName": "Xovep Stores",
      "headline": "Xovep Stores begins scheduled maintenance of automated logistics systems"
    },
    {
      "headlineId": "H006",
      "barIx": 27,
      "companyId": 0,
      "companyName": "Zrovex Industries",
      "headline": "Zrovex Industries wins industry award for excellence in renewable storage"
    },
    {
      "headlineId": "H007",
      "barIx": 29,
      "companyId": 3,
      "companyName": "Orevex Renewables",
      "headline": "Orevex Renewables faces regulatory review of precision manufacturing practices"
    },
    {
      "headlineId": "H008",
      "barIx": 34,
      "companyId": 0,
      "companyName": "Zrovex Industries",
      "headline": "Zrovex Industries loses key contract in Latin America to competitor"
    },
    {
      "headlineId": "H009",
      "barIx": 39,
      "companyId": 2,
      "companyName": "Nerven Grid",
      "headline": "Nerven Grid expands operations into Europe markets"
    },
    {
      "headlineId": "H010",
      "barIx": 40,
      "companyId": 1,
      "companyName": "Xovep Stores",
      "headline": "Xovep Stores sees 15% drop in new customer orders this quarter"
    },
    {
      "headlineId": "H011",
      "barIx": 41,
      "companyId": 3,
      "companyName": "Orevex Renewables",
      "headline": "Orevex Renewables enters joint venture with a multinational manufacturer"
    },
    {
      "headlineId": "H012",
      "barIx": 43,
      "companyId": 2,
      "companyName": "Nerven Grid",
      "headline": "Nerven Grid reports rising costs pressuring margins in renewable storage"
    }
  ]
}