{
  "session": "13312",
  "companyCount": 3,
  "headlineCount": 6,
  "companies": [
    {
      "companyId": 0,
      "name": "Jorvyl Securities",
      "headlineCount": 3,
      "firstBarIx": 28,
      "headlineIds": [
        "H001",
        "H005",
        "H006"
      ],
      "sampleHeadlines": [
        "Jorvyl Securities signs multi-year partnership with a major logistics provider",
        "Jorvyl Securities reports strong demand in Scandinavia, raises outlook",
        "Jorvyl Securities names new head of digital payments division"
      ]
    },
    {
      "companyId": 1,
      "name": "Pleven Trading Co",
      "headlineCount": 1,
      "firstBarIx": 37,
      "headlineIds": [
        "H002"
      ],
      "sampleHeadlines": [
        "Pleven Trading Co warns of supply chain disruptions affecting North America operations"
      ]
    },
    {
      "companyId": 2,
      "name": "Zelvel Capital",
      "headlineCount": 2,
      "firstBarIx": 42,
      "headlineIds": [
        "H003",
        "H004"
      ],
      "sampleHeadlines": [
        "Zelvel Capital secures $800M contract with a leading cloud platform",
        "Zelvel Capital faces class action over process automation service disruption"
      ]
    }
  ],
  "headlines": [
    {
      "headlineId": "H001",
      "barIx": 28,
      "companyId": 0,
      "companyName": "Jorvyl Securities",
      "headline": "Jorvyl Securities signs multi-year partnership with a major logistics provider"
    },
    {
      "headlineId": "H002",
      "barIx": 37,
      "companyId": 1,
      "companyName": "Pleven Trading Co",
      "headline": "Pleven Trading Co warns of supply chain disruptions affecting North America operations"
    },
    {
      "headlineId": "H003",
      "barIx": 42,
      "companyId": 2,
      "companyName": "Zelvel Capital",
      "headline": "Zelvel Capital secures $800M contract with a leading cloud platform"
    },
    {
      "headlineId": "H004",
      "barIx": 46,
      "companyId": 2,
      "companyName": "Zelvel Capital",
      "headline": "Zelvel Capital faces class action over process automation service disruption"
    },
    {
      "headlineId": "H005",
      "barIx": 48,
      "companyId": 0,
      "companyName": "Jorvyl Securities",
      "headline": "Jorvyl Securities reports strong demand in Scandinavia, raises outlook"
    },
    {
      "headlineId": "H006",
      "barIx": 49,
      "companyId": 0,
      "companyName": "Jorvyl Securities",
      "headline": "Jorvyl Securities names new head of digital payments division"
    }
  ]
}