{
  "session": "13978",
  "companyCount": 3,
  "headlineCount": 10,
  "companies": [
    {
      "companyId": 0,
      "name": "Relvon Fuels",
      "headlineCount": 3,
      "firstBarIx": 7,
      "headlineIds": [
        "H001",
        "H002",
        "H007"
      ],
      "sampleHeadlines": [
        "Relvon Fuels files for regulatory approval of new cloud infrastructure offering",
        "Relvon Fuels expands operations into Central Europe markets",
        "Relvon Fuels misses quarterly revenue estimates by 7%"
      ]
    },
    {
      "companyId": 1,
      "name": "Creven Securities",
      "headlineCount": 4,
      "firstBarIx": 14,
      "headlineIds": [
        "H003",
        "H004",
        "H005",
        "H010"
      ],
      "sampleHeadlines": [
        "Creven Securities secures $320M contract with a national infrastructure agency",
        "Creven Securities warns of supply chain disruptions affecting Scandinavia operations",
        "Creven Securities names new head of wireless connectivity division"
      ]
    },
    {
      "companyId": 2,
      "name": "Strynal Industries",
      "headlineCount": 3,
      "firstBarIx": 31,
      "headlineIds": [
        "H006",
        "H008",
        "H009"
      ],
      "sampleHeadlines": [
        "Strynal Industries opens new office in Scandinavia",
        "Strynal Industries to host investor day focused on cloud infrastructure strategy",
        "Strynal Industries explores strategic alternatives for precision manufacturing unit"
      ]
    }
  ],
  "headlines": [
    {
      "headlineId": "H001",
      "barIx": 7,
      "companyId": 0,
      "companyName": "Relvon Fuels",
      "headline": "Relvon Fuels files for regulatory approval of new cloud infrastructure offering"
    },
    {
      "headlineId": "H002",
      "barIx": 7,
      "companyId": 0,
      "companyName": "Relvon Fuels",
      "headline": "Relvon Fuels expands operations into Central Europe markets"
    },
    {
      "headlineId": "H003",
      "barIx": 14,
      "companyId": 1,
      "companyName": "Creven Securities",
      "headline": "Creven Securities secures $320M contract with a national infrastructure agency"
    },
    {
      "headlineId": "H004",
      "barIx": 22,
      "companyId": 1,
      "companyName": "Creven Securities",
      "headline": "Creven Securities warns of supply chain disruptions affecting Scandinavia operations"
    },
    {
      "headlineId": "H005",
      "barIx": 27,
      "companyId": 1,
      "companyName": "Creven Securities",
      "headline": "Creven Securities names new head of wireless connectivity division"
    },
    {
      "headlineId": "H006",
      "barIx": 31,
      "companyId": 2,
      "companyName": "Strynal Industries",
      "headline": "Strynal Industries opens new office in Scandinavia"
    },
    {
      "headlineId": "H007",
      "barIx": 32,
      "companyId": 0,
      "companyName": "Relvon Fuels",
      "headline": "Relvon Fuels misses quarterly revenue estimates by 7%"
    },
    {
      "headlineId": "H008",
      "barIx": 39,
      "companyId": 2,
      "companyName": "Strynal Industries",
      "headline": "Strynal Industries to host investor day focused on cloud infrastructure strategy"
    },
    {
      "headlineId": "H009",
      "barIx": 41,
      "companyId": 2,
      "companyName": "Strynal Industries",
      "headline": "Strynal Industries explores strategic alternatives for precision manufacturing unit"
    },
    {
      "headlineId": "H010",
      "barIx": 48,
      "companyId": 1,
      "companyName": "Creven Securities",
      "headline": "Creven Securities faces regulatory review of data analytics practices"
    }
  ]
}