{
  "session": "13997",
  "companyCount": 3,
  "headlineCount": 8,
  "companies": [
    {
      "companyId": 0,
      "name": "Jorvis Fuels",
      "headlineCount": 4,
      "firstBarIx": 6,
      "headlineIds": [
        "H001",
        "H003",
        "H004",
        "H008"
      ],
      "sampleHeadlines": [
        "Jorvis Fuels achieves key regulatory milestone ahead of schedule",
        "Jorvis Fuels names new head of supply chain optimization division",
        "Jorvis Fuels secures $250M contract with an international consortium"
      ]
    },
    {
      "companyId": 1,
      "name": "Wyrnor Solutions",
      "headlineCount": 2,
      "firstBarIx": 13,
      "headlineIds": [
        "H002",
        "H007"
      ],
      "sampleHeadlines": [
        "Wyrnor Solutions completes strategic acquisition to strengthen supply chain optimization",
        "Wyrnor Solutions delays product launch in supply chain optimization segment"
      ]
    },
    {
      "companyId": 2,
      "name": "Yorven Labs",
      "headlineCount": 2,
      "firstBarIx": 23,
      "headlineIds": [
        "H005",
        "H006"
      ],
      "sampleHeadlines": [
        "Yorven Labs faces class action over automated logistics service disruption",
        "Yorven Labs wins industry award for excellence in digital payments"
      ]
    }
  ],
  "headlines": [
    {
      "headlineId": "H001",
      "barIx": 6,
      "companyId": 0,
      "companyName": "Jorvis Fuels",
      "headline": "Jorvis Fuels achieves key regulatory milestone ahead of schedule"
    },
    {
      "headlineId": "H002",
      "barIx": 13,
      "companyId": 1,
      "companyName": "Wyrnor Solutions",
      "headline": "Wyrnor Solutions completes strategic acquisition to strengthen supply chain optimization"
    },
    {
      "headlineId": "H003",
      "barIx": 18,
      "companyId": 0,
      "companyName": "Jorvis Fuels",
      "headline": "Jorvis Fuels names new head of supply chain optimization division"
    },
    {
      "headlineId": "H004",
      "barIx": 18,
      "companyId": 0,
      "companyName": "Jorvis Fuels",
      "headline": "Jorvis Fuels secures $250M contract with an international consortium"
    },
    {
      "headlineId": "H005",
      "barIx": 23,
      "companyId": 2,
      "companyName": "Yorven Labs",
      "headline": "Yorven Labs faces class action over automated logistics service disruption"
    },
    {
      "headlineId": "H006",
      "barIx": 30,
      "companyId": 2,
      "companyName": "Yorven Labs",
      "headline": "Yorven Labs wins industry award for excellence in digital payments"
    },
    {
      "headlineId": "H007",
      "barIx": 31,
      "companyId": 1,
      "companyName": "Wyrnor Solutions",
      "headline": "Wyrnor Solutions delays product launch in supply chain optimization segment"
    },
    {
      "headlineId": "H008",
      "barIx": 38,
      "companyId": 0,
      "companyName": "Jorvis Fuels",
      "headline": "Jorvis Fuels to present at Annual Industry Forum"
    }
  ]
}