{
  "session": "12078",
  "companyCount": 4,
  "headlineCount": 9,
  "companies": [
    {
      "companyId": 0,
      "name": "Ixenis Outlets",
      "headlineCount": 2,
      "firstBarIx": 6,
      "headlineIds": [
        "H001",
        "H002"
      ],
      "sampleHeadlines": [
        "Ixenis Outlets wins industry award for excellence in renewable storage",
        "Ixenis Outlets reports strong demand in Middle East, raises outlook"
      ]
    },
    {
      "companyId": 1,
      "name": "Talvix Holdings",
      "headlineCount": 2,
      "firstBarIx": 13,
      "headlineIds": [
        "H003",
        "H006"
      ],
      "sampleHeadlines": [
        "Talvix Holdings publishes annual sustainability report",
        "Talvix Holdings sees 8% drop in new customer orders this quarter"
      ]
    },
    {
      "companyId": 2,
      "name": "Xovep Stores",
      "headlineCount": 2,
      "firstBarIx": 19,
      "headlineIds": [
        "H004",
        "H008"
      ],
      "sampleHeadlines": [
        "Xovep Stores opens new office in North America",
        "Xovep Stores explores strategic alternatives for process automation unit"
      ]
    },
    {
      "companyId": 3,
      "name": "Arnik Commerce",
      "headlineCount": 3,
      "firstBarIx": 19,
      "headlineIds": [
        "H005",
        "H007",
        "H009"
      ],
      "sampleHeadlines": [
        "Arnik Commerce confirms participation in Tech Leadership Conference",
        "Arnik Commerce loses key contract in Europe to competitor",
        "Arnik Commerce secures $75M contract with an international consortium"
      ]
    }
  ],
  "headlines": [
    {
      "headlineId": "H001",
      "barIx": 6,
      "companyId": 0,
      "companyName": "Ixenis Outlets",
      "headline": "Ixenis Outlets wins industry award for excellence in renewable storage"
    },
    {
      "headlineId": "H002",
      "barIx": 8,
      "companyId": 0,
      "companyName": "Ixenis Outlets",
      "headline": "Ixenis Outlets reports strong demand in Middle East, raises outlook"
    },
    {
      "headlineId": "H003",
      "barIx": 13,
      "companyId": 1,
      "companyName": "Talvix Holdings",
      "headline": "Talvix Holdings publishes annual sustainability report"
    },
    {
      "headlineId": "H004",
      "barIx": 19,
      "companyId": 2,
      "companyName": "Xovep Stores",
      "headline": "Xovep Stores opens new office in North America"
    },
    {
      "headlineId": "H005",
      "barIx": 19,
      "companyId": 3,
      "companyName": "Arnik Commerce",
      "headline": "Arnik Commerce confirms participation in Tech Leadership Conference"
    },
    {
      "headlineId": "H006",
      "barIx": 24,
      "companyId": 1,
      "companyName": "Talvix Holdings",
      "headline": "Talvix Holdings sees 8% drop in new customer orders this quarter"
    },
    {
      "headlineId": "H007",
      "barIx": 35,
      "companyId": 3,
      "companyName": "Arnik Commerce",
      "headline": "Arnik Commerce loses key contract in Europe to competitor"
    },
    {
      "headlineId": "H008",
      "barIx": 39,
      "companyId": 2,
      "companyName": "Xovep Stores",
      "headline": "Xovep Stores explores strategic alternatives for process automation unit"
    },
    {
      "headlineId": "H009",
      "barIx": 41,
      "companyId": 3,
      "companyName": "Arnik Commerce",
      "headline": "Arnik Commerce secures $75M contract with an international consortium"
    }
  ]
}