{
  "session": "8541",
  "companyCount": 4,
  "headlineCount": 12,
  "companies": [
    {
      "companyId": 0,
      "name": "Joval Brands",
      "headlineCount": 4,
      "firstBarIx": 3,
      "headlineIds": [
        "H001",
        "H004",
        "H007",
        "H008"
      ],
      "sampleHeadlines": [
        "Joval Brands sees 5% margin improvement in latest quarter",
        "Joval Brands revises long-term strategy with focus on renewable storage",
        "Joval Brands reports 18% increase in customer acquisition"
      ]
    },
    {
      "companyId": 1,
      "name": "Ixenix Technologies",
      "headlineCount": 4,
      "firstBarIx": 6,
      "headlineIds": [
        "H002",
        "H009",
        "H010",
        "H012"
      ],
      "sampleHeadlines": [
        "Ixenix Technologies reports 3% increase in customer acquisition",
        "Ixenix Technologies sees mixed results in wireless connectivity pilot program",
        "Ixenix Technologies wins industry award for excellence in enterprise software"
      ]
    },
    {
      "companyId": 2,
      "name": "Frelex Outlets",
      "headlineCount": 3,
      "firstBarIx": 8,
      "headlineIds": [
        "H003",
        "H005",
        "H006"
      ],
      "sampleHeadlines": [
        "Frelex Outlets reports strong demand in Europe, raises outlook",
        "Frelex Outlets reports record quarterly revenue, up 18% year-over-year",
        "Frelex Outlets secures $500M contract with a leading cloud platform"
      ]
    },
    {
      "companyId": 3,
      "name": "Nolvav Commerce",
      "headlineCount": 1,
      "firstBarIx": 44,
      "headlineIds": [
        "H011"
      ],
      "sampleHeadlines": [
        "Nolvav Commerce secures $50M contract with a leading cloud platform"
      ]
    }
  ],
  "headlines": [
    {
      "headlineId": "H001",
      "barIx": 3,
      "companyId": 0,
      "companyName": "Joval Brands",
      "headline": "Joval Brands sees 5% margin improvement in latest quarter"
    },
    {
      "headlineId": "H002",
      "barIx": 6,
      "companyId": 1,
      "companyName": "Ixenix Technologies",
      "headline": "Ixenix Technologies reports 3% increase in customer acquisition"
    },
    {
      "headlineId": "H003",
      "barIx": 8,
      "companyId": 2,
      "companyName": "Frelex Outlets",
      "headline": "Frelex Outlets reports strong demand in Europe, raises outlook"
    },
    {
      "headlineId": "H004",
      "barIx": 20,
      "companyId": 0,
      "companyName": "Joval Brands",
      "headline": "Joval Brands revises long-term strategy with focus on renewable storage"
    },
    {
      "headlineId": "H005",
      "barIx": 21,
      "companyId": 2,
      "companyName": "Frelex Outlets",
      "headline": "Frelex Outlets reports record quarterly revenue, up 18% year-over-year"
    },
    {
      "headlineId": "H006",
      "barIx": 23,
      "companyId": 2,
      "companyName": "Frelex Outlets",
      "headline": "Frelex Outlets secures $500M contract with a leading cloud platform"
    },
    {
      "headlineId": "H007",
      "barIx": 23,
      "companyId": 0,
      "companyName": "Joval Brands",
      "headline": "Joval Brands reports 18% increase in customer acquisition"
    },
    {
      "headlineId": "H008",
      "barIx": 33,
      "companyId": 0,
      "companyName": "Joval Brands",
      "headline": "Joval Brands revises long-term strategy with focus on precision manufacturing"
    },
    {
      "headlineId": "H009",
      "barIx": 33,
      "companyId": 1,
      "companyName": "Ixenix Technologies",
      "headline": "Ixenix Technologies sees mixed results in wireless connectivity pilot program"
    },
    {
      "headlineId": "H010",
      "barIx": 42,
      "companyId": 1,
      "companyName": "Ixenix Technologies",
      "headline": "Ixenix Technologies wins industry award for excellence in enterprise software"
    },
    {
      "headlineId": "H011",
      "barIx": 44,
      "companyId": 3,
      "companyName": "Nolvav Commerce",
      "headline": "Nolvav Commerce secures $50M contract with a leading cloud platform"
    },
    {
      "headlineId": "H012",
      "barIx": 46,
      "companyId": 1,
      "companyName": "Ixenix Technologies",
      "headline": "Ixenix Technologies opens new office in Scandinavia"
    }
  ]
}