{
  "session": "6308",
  "companyCount": 4,
  "headlineCount": 8,
  "companies": [
    {
      "companyId": 0,
      "name": "Jovor Networks",
      "headlineCount": 3,
      "firstBarIx": 0,
      "headlineIds": [
        "H001",
        "H002",
        "H006"
      ],
      "sampleHeadlines": [
        "Jovor Networks completes planned facility upgrade in Scandinavia",
        "Jovor Networks sees 3% drop in new customer orders this quarter",
        "Jovor Networks reports 25% decline in operating income"
      ]
    },
    {
      "companyId": 1,
      "name": "Ulvyn Microchips",
      "headlineCount": 2,
      "firstBarIx": 8,
      "headlineIds": [
        "H003",
        "H004"
      ],
      "sampleHeadlines": [
        "Ulvyn Microchips wins industry award for excellence in enterprise software",
        "Ulvyn Microchips files routine patent applications in enterprise software"
      ]
    },
    {
      "companyId": 2,
      "name": "Ilval Financial",
      "headlineCount": 1,
      "firstBarIx": 17,
      "headlineIds": [
        "H005"
      ],
      "sampleHeadlines": [
        "Ilval Financial to host investor day focused on precision manufacturing strategy"
      ]
    },
    {
      "companyId": 3,
      "name": "Relvan Software",
      "headlineCount": 2,
      "firstBarIx": 38,
      "headlineIds": [
        "H007",
        "H008"
      ],
      "sampleHeadlines": [
        "Relvan Software announces $9.6B share buyback program",
        "Relvan Software reports 15% increase in customer acquisition"
      ]
    }
  ],
  "headlines": [
    {
      "headlineId": "H001",
      "barIx": 0,
      "companyId": 0,
      "companyName": "Jovor Networks",
      "headline": "Jovor Networks completes planned facility upgrade in Scandinavia"
    },
    {
      "headlineId": "H002",
      "barIx": 8,
      "companyId": 0,
      "companyName": "Jovor Networks",
      "headline": "Jovor Networks sees 3% drop in new customer orders this quarter"
    },
    {
      "headlineId": "H003",
      "barIx": 8,
      "companyId": 1,
      "companyName": "Ulvyn Microchips",
      "headline": "Ulvyn Microchips wins industry award for excellence in enterprise software"
    },
    {
      "headlineId": "H004",
      "barIx": 11,
      "companyId": 1,
      "companyName": "Ulvyn Microchips",
      "headline": "Ulvyn Microchips files routine patent applications in enterprise software"
    },
    {
      "headlineId": "H005",
      "barIx": 17,
      "companyId": 2,
      "companyName": "Ilval Financial",
      "headline": "Ilval Financial to host investor day focused on precision manufacturing strategy"
    },
    {
      "headlineId": "H006",
      "barIx": 29,
      "companyId": 0,
      "companyName": "Jovor Networks",
      "headline": "Jovor Networks reports 25% decline in operating income"
    },
    {
      "headlineId": "H007",
      "barIx": 38,
      "companyId": 3,
      "companyName": "Relvan Software",
      "headline": "Relvan Software announces $9.6B share buyback program"
    },
    {
      "headlineId": "H008",
      "barIx": 39,
      "companyId": 3,
      "companyName": "Relvan Software",
      "headline": "Relvan Software reports 15% increase in customer acquisition"
    }
  ]
}