{
  "session": "7375",
  "companyCount": 4,
  "headlineCount": 10,
  "companies": [
    {
      "companyId": 0,
      "name": "Nerval Biopharma",
      "headlineCount": 3,
      "firstBarIx": 5,
      "headlineIds": [
        "H001",
        "H008",
        "H009"
      ],
      "sampleHeadlines": [
        "Nerval Biopharma reports 5% increase in customer acquisition",
        "Nerval Biopharma recalls products in enterprise software line due to quality concerns",
        "Nerval Biopharma delays product launch in renewable storage segment"
      ]
    },
    {
      "companyId": 1,
      "name": "Grevel Diagnostics",
      "headlineCount": 3,
      "firstBarIx": 7,
      "headlineIds": [
        "H002",
        "H006",
        "H010"
      ],
      "sampleHeadlines": [
        "Grevel Diagnostics opens new office in Europe",
        "Grevel Diagnostics faces class action over data analytics service disruption",
        "Grevel Diagnostics loses key contract in Scandinavia to competitor"
      ]
    },
    {
      "companyId": 2,
      "name": "Frelis Genomics",
      "headlineCount": 2,
      "firstBarIx": 13,
      "headlineIds": [
        "H003",
        "H004"
      ],
      "sampleHeadlines": [
        "Frelis Genomics to host investor day focused on data analytics strategy",
        "Frelis Genomics explores strategic alternatives for cloud infrastructure unit"
      ]
    },
    {
      "companyId": 3,
      "name": "Calvos Genomics",
      "headlineCount": 2,
      "firstBarIx": 27,
      "headlineIds": [
        "H005",
        "H007"
      ],
      "sampleHeadlines": [
        "Calvos Genomics revises long-term strategy with focus on supply chain optimization",
        "Calvos Genomics announces breakthrough in automated logistics"
      ]
    }
  ],
  "headlines": [
    {
      "headlineId": "H001",
      "barIx": 5,
      "companyId": 0,
      "companyName": "Nerval Biopharma",
      "headline": "Nerval Biopharma reports 5% increase in customer acquisition"
    },
    {
      "headlineId": "H002",
      "barIx": 7,
      "companyId": 1,
      "companyName": "Grevel Diagnostics",
      "headline": "Grevel Diagnostics opens new office in Europe"
    },
    {
      "headlineId": "H003",
      "barIx": 13,
      "companyId": 2,
      "companyName": "Frelis Genomics",
      "headline": "Frelis Genomics to host investor day focused on data analytics strategy"
    },
    {
      "headlineId": "H004",
      "barIx": 23,
      "companyId": 2,
      "companyName": "Frelis Genomics",
      "headline": "Frelis Genomics explores strategic alternatives for cloud infrastructure unit"
    },
    {
      "headlineId": "H005",
      "barIx": 27,
      "companyId": 3,
      "companyName": "Calvos Genomics",
      "headline": "Calvos Genomics revises long-term strategy with focus on supply chain optimization"
    },
    {
      "headlineId": "H006",
      "barIx": 31,
      "companyId": 1,
      "companyName": "Grevel Diagnostics",
      "headline": "Grevel Diagnostics faces class action over data analytics service disruption"
    },
    {
      "headlineId": "H007",
      "barIx": 34,
      "companyId": 3,
      "companyName": "Calvos Genomics",
      "headline": "Calvos Genomics announces breakthrough in automated logistics"
    },
    {
      "headlineId": "H008",
      "barIx": 40,
      "companyId": 0,
      "companyName": "Nerval Biopharma",
      "headline": "Nerval Biopharma recalls products in enterprise software line due to quality concerns"
    },
    {
      "headlineId": "H009",
      "barIx": 41,
      "companyId": 0,
      "companyName": "Nerval Biopharma",
      "headline": "Nerval Biopharma delays product launch in renewable storage segment"
    },
    {
      "headlineId": "H010",
      "barIx": 44,
      "companyId": 1,
      "companyName": "Grevel Diagnostics",
      "headline": "Grevel Diagnostics loses key contract in Scandinavia to competitor"
    }
  ]
}